funfoobar/__init__.py
funfoobar/command_line.py
funfoobar/text.py
funfoobar-0.9.data/scripts/funniest-joke
funfoobar-0.9.dist-info/METADATA
funfoobar-0.9.dist-info/WHEEL
funfoobar-0.9.dist-info/entry_points.txt
funfoobar-0.9.dist-info/top_level.txt
funfoobar-0.9.dist-info/RECORD
