Metadata-Version: 2.1
Name: funfoobar
Version: 0.9
Summary: The funniest joke in the world
Home-page: http://github.com/joehmchiu/funfoobar
Author: Joe Chiu
Author-email: joehmchiu@gmail.com
License: MIT
Keywords: funniest joke comedy flying circus
Platform: UNKNOWN
Classifier: Development Status :: 3 - Alpha
Classifier: License :: OSI Approved :: MIT License
Classifier: Programming Language :: Python :: 3.6
Classifier: Topic :: Text Processing :: Linguistic
Requires-Dist: markdown
